{
	"description": "项目配置文件。",
	"setting": {
		"urlCheck": true,
		"es6": true,
		"enhance": true,
		"postcss": true,
		"minified": true,
		"newFeature": true,
		"coverView": true,
		"nodeModules": true,
		"autoAudits": false,
		"uglifyFileName": true,
		"checkInvalidKey": true,
		"checkSiteMap": true,
		"uploadWithSourceMap": true,
		"babelSetting": {
			"ignore": [],
			"disablePlugins": [],
			"outputPath": ""
		}
	},
	"compileType": "miniprogram",
	"libVersion": "2.6.6",
	"appid": "wxd145d8a6e951dd1b",
	"projectname": "BC",
	"isGameTourist": false,
	"simulatorType": "wechat",
	"simulatorPluginLibVersion": {},
	"condition": {
		"search": {
			"current": -1,
			"list": []
		},
		"conversation": {
			"current": -1,
			"list": []
		},
		"plugin": {
			"current": -1,
			"list": []
		},
		"game": {
			"currentL": -1,
			"list": []
		},
		"miniprogram": {
			"current": 0,
			"list": [
				{
					"id": 0,
					"name": "商品详情",
					"pathName": "pages/goods/goodsdetail/goodsdetail?goods_id=1126",
					"query": "",
					"scene": null
				},
				{
					"id": -1,
					"name": "门店活动列表",
					"pathName": "pages/goods/lineActivity/lineActivity",
					"query": "",
					"scene": null
				},
				{
					"id": -1,
					"name": "门店活动详情页",
					"pathName": "pages/goods/lineParticulars/lineParticulars",
					"query": "",
					"scene": null
				},
				{
					"id": -1,
					"name": "申请成为极选师",
					"pathName": "pages/member/kolApply/kolApply",
					"query": "",
					"scene": null
				},
				{
					"id": -1,
					"name": "卡券",
					"pathName": "pages/member/electronic/electronic",
					"query": "",
					"scene": null
				}
			]
		}
	}
}